yasf/__init__.py
yasf/__version__.py
yasf/py.typed
yasf/yasf.py
yasf-0.0.5.dist-info/LICENSE
yasf-0.0.5.dist-info/LICENSE.txt
yasf-0.0.5.dist-info/METADATA
yasf-0.0.5.dist-info/WHEEL
yasf-0.0.5.dist-info/top_level.txt
yasf-0.0.5.dist-info/RECORD
