Metadata-Version: 2.1
Name: yasf
Version: 0.0.5
Summary: Yet Another Structured Formatter
Home-page: https://github.com/jamesabel/yasf
Download-URL: https://github.com/jamesabel/yasf/archive/master.zip
Author: James Abel
Author-email: j@abel.co
License: MIT License
Keywords: formatting,utility
License-File: LICENSE
License-File: LICENSE.txt
